{"nodes": [{"id": "users_vihaannathan_documents_pureunix_shell_sh_c", "label": "sh.c", "file_type": "code", "source_file": "shell/sh.c", "source_location": "L1"}, {"id": "users_vihaannathan_documents_pureunix_shell_sh_shell_out_write", "label": "shell_out_write()", "file_type": "code", "source_file": "shell/sh.c", "source_location": "L15"}, {"id": "shell_output_t", "label": "shell_output_t", "file_type": "code", "source_file": "", "source_location": "", "origin_file": "/Users/vihaannathan/Documents/PureUNIX/shell/sh.c"}, {"id": "users_vihaannathan_documents_pureunix_shell_sh_shell_out_puts", "label": "shell_out_puts()", "file_type": "code", "source_file": "shell/sh.c", "source_location": "L34"}, {"id": "users_vihaannathan_documents_pureunix_shell_sh_shell_out_printf", "label": "shell_out_printf()", "file_type": "code", "source_file": "shell/sh.c", "source_location": "L39"}, {"id": "users_vihaannathan_documents_pureunix_shell_sh_exec_external", "label": "exec_external()", "file_type": "code", "source_file": "shell/sh.c", "source_location": "L49"}, {"id": "shell_context_t", "label": "shell_context_t", "file_type": "code", "source_file": "", "source_location": "", "origin_file": "/Users/vihaannathan/Documents/PureUNIX/shell/sh.c"}, {"id": "shell_command_t", "label": "shell_command_t", "file_type": "code", "source_file": "", "source_location": "", "origin_file": "/Users/vihaannathan/Documents/PureUNIX/shell/sh.c"}, {"id": "users_vihaannathan_documents_pureunix_shell_sh_run_command", "label": "run_command()", "file_type": "code", "source_file": "shell/sh.c", "source_location": "L83"}, {"id": "users_vihaannathan_documents_pureunix_shell_sh_read_input_redirection", "label": "read_input_redirection()", "file_type": "code", "source_file": "shell/sh.c", "source_location": "L95"}, {"id": "users_vihaannathan_documents_pureunix_shell_sh_shell_execute_line", "label": "shell_execute_line()", "file_type": "code", "source_file": "shell/sh.c", "source_location": "L116"}, {"id": "users_vihaannathan_documents_pureunix_shell_sh_shell_run", "label": "shell_run()", "file_type": "code", "source_file": "shell/sh.c", "source_location": "L179"}], "edges": [{"source": "users_vihaannathan_documents_pureunix_shell_sh_c", "target": "users_vihaannathan_documents_pureunix_shell_shell_internal_h", "relation": "imports", "context": "import", "confidence": "EXTRACTED", "source_file": "shell/sh.c", "source_location": "L1", "weight": 1.0}, {"source": "users_vihaannathan_documents_pureunix_shell_sh_c", "target": "stdarg", "relation": "imports", "context": "import", "confidence": "EXTRACTED", "source_file": "shell/sh.c", "source_location": "L2", "weight": 1.0}, {"source": "users_vihaannathan_documents_pureunix_shell_sh_c", "target": "config", "relation": "imports", "context": "import", "confidence": "EXTRACTED", "source_file": "shell/sh.c", "source_location": "L3", "weight": 1.0}, {"source": "users_vihaannathan_documents_pureunix_shell_sh_c", "target": "elf", "relation": "imports", "context": "import", "confidence": "EXTRACTED", "source_file": "shell/sh.c", "source_location": "L4", "weight": 1.0}, {"source": "users_vihaannathan_documents_pureunix_shell_sh_c", "target": "memory", "relation": "imports", "context": "import", "confidence": "EXTRACTED", "source_file": "shell/sh.c", "source_location": "L5", "weight": 1.0}, {"source": "users_vihaannathan_documents_pureunix_shell_sh_c", "target": "stdio", "relation": "imports", "context": "import", "confidence": "EXTRACTED", "source_file": "shell/sh.c", "source_location": "L6", "weight": 1.0}, {"source": "users_vihaannathan_documents_pureunix_shell_sh_c", "target": "string", "relation": "imports", "context": "import", "confidence": "EXTRACTED", "source_file": "shell/sh.c", "source_location": "L7", "weight": 1.0}, {"source": "users_vihaannathan_documents_pureunix_shell_sh_c", "target": "vfs", "relation": "imports", "context": "import", "confidence": "EXTRACTED", "source_file": "shell/sh.c", "source_location": "L8", "weight": 1.0}, {"source": "users_vihaannathan_documents_pureunix_shell_sh_c", "target": "vga", "relation": "imports", "context": "import", "confidence": "EXTRACTED", "source_file": "shell/sh.c", "source_location": "L9", "weight": 1.0}, {"source": "users_vihaannathan_documents_pureunix_shell_sh_c", "target": "users_vihaannathan_documents_pureunix_shell_sh_shell_out_write", "relation": "contains", "confidence": "EXTRACTED", "source_file": "shell/sh.c", "source_location": "L15", "weight": 1.0}, {"source": "users_vihaannathan_documents_pureunix_shell_sh_shell_out_write", "target": "shell_output_t", "relation": "references", "confidence": "EXTRACTED", "source_file": "shell/sh.c", "source_location": "L15", "weight": 1.0, "context": "parameter_type"}, {"source": "users_vihaannathan_documents_pureunix_shell_sh_c", "target": "users_vihaannathan_documents_pureunix_shell_sh_shell_out_puts", "relation": "contains", "confidence": "EXTRACTED", "source_file": "shell/sh.c", "source_location": "L34", "weight": 1.0}, {"source": "users_vihaannathan_documents_pureunix_shell_sh_shell_out_puts", "target": "shell_output_t", "relation": "references", "confidence": "EXTRACTED", "source_file": "shell/sh.c", "source_location": "L34", "weight": 1.0, "context": "parameter_type"}, {"source": "users_vihaannathan_documents_pureunix_shell_sh_c", "target": "users_vihaannathan_documents_pureunix_shell_sh_shell_out_printf", "relation": "contains", "confidence": "EXTRACTED", "source_file": "shell/sh.c", "source_location": "L39", "weight": 1.0}, {"source": "users_vihaannathan_documents_pureunix_shell_sh_shell_out_printf", "target": "shell_output_t", "relation": "references", "confidence": "EXTRACTED", "source_file": "shell/sh.c", "source_location": "L39", "weight": 1.0, "context": "parameter_type"}, {"source": "users_vihaannathan_documents_pureunix_shell_sh_c", "target": "users_vihaannathan_documents_pureunix_shell_sh_exec_external", "relation": "contains", "confidence": "EXTRACTED", "source_file": "shell/sh.c", "source_location": "L49", "weight": 1.0}, {"source": "users_vihaannathan_documents_pureunix_shell_sh_exec_external", "target": "shell_context_t", "relation": "references", "confidence": "EXTRACTED", "source_file": "shell/sh.c", "source_location": "L49", "weight": 1.0, "context": "parameter_type"}, {"source": "users_vihaannathan_documents_pureunix_shell_sh_exec_external", "target": "shell_command_t", "relation": "references", "confidence": "EXTRACTED", "source_file": "shell/sh.c", "source_location": "L49", "weight": 1.0, "context": "parameter_type"}, {"source": "users_vihaannathan_documents_pureunix_shell_sh_exec_external", "target": "shell_output_t", "relation": "references", "confidence": "EXTRACTED", "source_file": "shell/sh.c", "source_location": "L49", "weight": 1.0, "context": "parameter_type"}, {"source": "users_vihaannathan_documents_pureunix_shell_sh_c", "target": "users_vihaannathan_documents_pureunix_shell_sh_run_command", "relation": "contains", "confidence": "EXTRACTED", "source_file": "shell/sh.c", "source_location": "L83", "weight": 1.0}, {"source": "users_vihaannathan_documents_pureunix_shell_sh_run_command", "target": "shell_context_t", "relation": "references", "confidence": "EXTRACTED", "source_file": "shell/sh.c", "source_location": "L83", "weight": 1.0, "context": "parameter_type"}, {"source": "users_vihaannathan_documents_pureunix_shell_sh_run_command", "target": "shell_command_t", "relation": "references", "confidence": "EXTRACTED", "source_file": "shell/sh.c", "source_location": "L83", "weight": 1.0, "context": "parameter_type"}, {"source": "users_vihaannathan_documents_pureunix_shell_sh_run_command", "target": "shell_output_t", "relation": "references", "confidence": "EXTRACTED", "source_file": "shell/sh.c", "source_location": "L83", "weight": 1.0, "context": "parameter_type"}, {"source": "users_vihaannathan_documents_pureunix_shell_sh_c", "target": "users_vihaannathan_documents_pureunix_shell_sh_read_input_redirection", "relation": "contains", "confidence": "EXTRACTED", "source_file": "shell/sh.c", "source_location": "L95", "weight": 1.0}, {"source": "users_vihaannathan_documents_pureunix_shell_sh_read_input_redirection", "target": "shell_context_t", "relation": "references", "confidence": "EXTRACTED", "source_file": "shell/sh.c", "source_location": "L95", "weight": 1.0, "context": "parameter_type"}, {"source": "users_vihaannathan_documents_pureunix_shell_sh_c", "target": "users_vihaannathan_documents_pureunix_shell_sh_shell_execute_line", "relation": "contains", "confidence": "EXTRACTED", "source_file": "shell/sh.c", "source_location": "L116", "weight": 1.0}, {"source": "users_vihaannathan_documents_pureunix_shell_sh_c", "target": "users_vihaannathan_documents_pureunix_shell_sh_shell_run", "relation": "contains", "confidence": "EXTRACTED", "source_file": "shell/sh.c", "source_location": "L179", "weight": 1.0}, {"source": "users_vihaannathan_documents_pureunix_shell_sh_shell_out_puts", "target": "users_vihaannathan_documents_pureunix_shell_sh_shell_out_write", "relation": "calls", "context": "call", "confidence": "EXTRACTED", "source_file": "shell/sh.c", "source_location": "L36", "weight": 1.0}, {"source": "users_vihaannathan_documents_pureunix_shell_sh_shell_out_printf", "target": "users_vihaannathan_documents_pureunix_shell_sh_shell_out_puts", "relation": "calls", "context": "call", "confidence": "EXTRACTED", "source_file": "shell/sh.c", "source_location": "L46", "weight": 1.0}, {"source": "users_vihaannathan_documents_pureunix_shell_sh_exec_external", "target": "users_vihaannathan_documents_pureunix_shell_sh_shell_out_printf", "relation": "calls", "context": "call", "confidence": "EXTRACTED", "source_file": "shell/sh.c", "source_location": "L56", "weight": 1.0}, {"source": "users_vihaannathan_documents_pureunix_shell_sh_run_command", "target": "users_vihaannathan_documents_pureunix_shell_sh_exec_external", "relation": "calls", "context": "call", "confidence": "EXTRACTED", "source_file": "shell/sh.c", "source_location": "L92", "weight": 1.0}, {"source": "users_vihaannathan_documents_pureunix_shell_sh_shell_execute_line", "target": "users_vihaannathan_documents_pureunix_shell_sh_read_input_redirection", "relation": "calls", "context": "call", "confidence": "EXTRACTED", "source_file": "shell/sh.c", "source_location": "L148", "weight": 1.0}, {"source": "users_vihaannathan_documents_pureunix_shell_sh_shell_execute_line", "target": "users_vihaannathan_documents_pureunix_shell_sh_run_command", "relation": "calls", "context": "call", "confidence": "EXTRACTED", "source_file": "shell/sh.c", "source_location": "L155", "weight": 1.0}, {"source": "users_vihaannathan_documents_pureunix_shell_sh_shell_run", "target": "users_vihaannathan_documents_pureunix_shell_sh_shell_execute_line", "relation": "calls", "context": "call", "confidence": "EXTRACTED", "source_file": "shell/sh.c", "source_location": "L187", "weight": 1.0}], "raw_calls": [{"caller_nid": "users_vihaannathan_documents_pureunix_shell_sh_shell_out_write", "callee": "vga_write_len", "is_member_call": false, "source_file": "/Users/vihaannathan/Documents/PureUNIX/shell/sh.c", "source_location": "L21", "receiver": null}, {"caller_nid": "users_vihaannathan_documents_pureunix_shell_sh_shell_out_write", "callee": "memcpy", "is_member_call": false, "source_file": "/Users/vihaannathan/Documents/PureUNIX/shell/sh.c", "source_location": "L28", "receiver": null}, {"caller_nid": "users_vihaannathan_documents_pureunix_shell_sh_shell_out_puts", "callee": "strlen", "is_member_call": false, "source_file": "/Users/vihaannathan/Documents/PureUNIX/shell/sh.c", "source_location": "L36", "receiver": null}, {"caller_nid": "users_vihaannathan_documents_pureunix_shell_sh_shell_out_printf", "callee": "va_start", "is_member_call": false, "source_file": "/Users/vihaannathan/Documents/PureUNIX/shell/sh.c", "source_location": "L43", "receiver": null}, {"caller_nid": "users_vihaannathan_documents_pureunix_shell_sh_shell_out_printf", "callee": "vsnprintf", "is_member_call": false, "source_file": "/Users/vihaannathan/Documents/PureUNIX/shell/sh.c", "source_location": "L44", "receiver": null}, {"caller_nid": "users_vihaannathan_documents_pureunix_shell_sh_shell_out_printf", "callee": "va_end", "is_member_call": false, "source_file": "/Users/vihaannathan/Documents/PureUNIX/shell/sh.c", "source_location": "L45", "receiver": null}, {"caller_nid": "users_vihaannathan_documents_pureunix_shell_sh_exec_external", "callee": "strchr", "is_member_call": false, "source_file": "/Users/vihaannathan/Documents/PureUNIX/shell/sh.c", "source_location": "L52", "receiver": null}, {"caller_nid": "users_vihaannathan_documents_pureunix_shell_sh_exec_external", "callee": "vfs_normalize", "is_member_call": false, "source_file": "/Users/vihaannathan/Documents/PureUNIX/shell/sh.c", "source_location": "L53", "receiver": null}, {"caller_nid": "users_vihaannathan_documents_pureunix_shell_sh_exec_external", "callee": "vfs_stat", "is_member_call": false, "source_file": "/Users/vihaannathan/Documents/PureUNIX/shell/sh.c", "source_location": "L55", "receiver": null}, {"caller_nid": "users_vihaannathan_documents_pureunix_shell_sh_exec_external", "callee": "elf_exec", "is_member_call": false, "source_file": "/Users/vihaannathan/Documents/PureUNIX/shell/sh.c", "source_location": "L59", "receiver": null}, {"caller_nid": "users_vihaannathan_documents_pureunix_shell_sh_exec_external", "callee": "strcmp", "is_member_call": false, "source_file": "/Users/vihaannathan/Documents/PureUNIX/shell/sh.c", "source_location": "L62", "receiver": null}, {"caller_nid": "users_vihaannathan_documents_pureunix_shell_sh_exec_external", "callee": "snprintf", "is_member_call": false, "source_file": "/Users/vihaannathan/Documents/PureUNIX/shell/sh.c", "source_location": "L63", "receiver": null}, {"caller_nid": "users_vihaannathan_documents_pureunix_shell_sh_exec_external", "callee": "vfs_stat", "is_member_call": false, "source_file": "/Users/vihaannathan/Documents/PureUNIX/shell/sh.c", "source_location": "L65", "receiver": null}, {"caller_nid": "users_vihaannathan_documents_pureunix_shell_sh_exec_external", "callee": "elf_exec", "is_member_call": false, "source_file": "/Users/vihaannathan/Documents/PureUNIX/shell/sh.c", "source_location": "L66", "receiver": null}, {"caller_nid": "users_vihaannathan_documents_pureunix_shell_sh_exec_external", "callee": "snprintf", "is_member_call": false, "source_file": "/Users/vihaannathan/Documents/PureUNIX/shell/sh.c", "source_location": "L70", "receiver": null}, {"caller_nid": "users_vihaannathan_documents_pureunix_shell_sh_exec_external", "callee": "vfs_stat", "is_member_call": false, "source_file": "/Users/vihaannathan/Documents/PureUNIX/shell/sh.c", "source_location": "L72", "receiver": null}, {"caller_nid": "users_vihaannathan_documents_pureunix_shell_sh_exec_external", "callee": "elf_exec", "is_member_call": false, "source_file": "/Users/vihaannathan/Documents/PureUNIX/shell/sh.c", "source_location": "L72", "receiver": null}, {"caller_nid": "users_vihaannathan_documents_pureunix_shell_sh_exec_external", "callee": "snprintf", "is_member_call": false, "source_file": "/Users/vihaannathan/Documents/PureUNIX/shell/sh.c", "source_location": "L75", "receiver": null}, {"caller_nid": "users_vihaannathan_documents_pureunix_shell_sh_exec_external", "callee": "vfs_stat", "is_member_call": false, "source_file": "/Users/vihaannathan/Documents/PureUNIX/shell/sh.c", "source_location": "L76", "receiver": null}, {"caller_nid": "users_vihaannathan_documents_pureunix_shell_sh_exec_external", "callee": "elf_exec", "is_member_call": false, "source_file": "/Users/vihaannathan/Documents/PureUNIX/shell/sh.c", "source_location": "L76", "receiver": null}, {"caller_nid": "users_vihaannathan_documents_pureunix_shell_sh_run_command", "callee": "shell_find_builtin", "is_member_call": false, "source_file": "/Users/vihaannathan/Documents/PureUNIX/shell/sh.c", "source_location": "L88", "receiver": null}, {"caller_nid": "users_vihaannathan_documents_pureunix_shell_sh_run_command", "callee": "fn", "is_member_call": true, "source_file": "/Users/vihaannathan/Documents/PureUNIX/shell/sh.c", "source_location": "L90", "receiver": null}, {"caller_nid": "users_vihaannathan_documents_pureunix_shell_sh_read_input_redirection", "callee": "vfs_normalize", "is_member_call": false, "source_file": "/Users/vihaannathan/Documents/PureUNIX/shell/sh.c", "source_location": "L100", "receiver": null}, {"caller_nid": "users_vihaannathan_documents_pureunix_shell_sh_read_input_redirection", "callee": "vfs_read_file", "is_member_call": false, "source_file": "/Users/vihaannathan/Documents/PureUNIX/shell/sh.c", "source_location": "L101", "receiver": null}, {"caller_nid": "users_vihaannathan_documents_pureunix_shell_sh_read_input_redirection", "callee": "kmalloc", "is_member_call": false, "source_file": "/Users/vihaannathan/Documents/PureUNIX/shell/sh.c", "source_location": "L104", "receiver": null}, {"caller_nid": "users_vihaannathan_documents_pureunix_shell_sh_read_input_redirection", "callee": "kfree", "is_member_call": false, "source_file": "/Users/vihaannathan/Documents/PureUNIX/shell/sh.c", "source_location": "L106", "receiver": null}, {"caller_nid": "users_vihaannathan_documents_pureunix_shell_sh_read_input_redirection", "callee": "memcpy", "is_member_call": false, "source_file": "/Users/vihaannathan/Documents/PureUNIX/shell/sh.c", "source_location": "L109", "receiver": null}, {"caller_nid": "users_vihaannathan_documents_pureunix_shell_sh_read_input_redirection", "callee": "kfree", "is_member_call": false, "source_file": "/Users/vihaannathan/Documents/PureUNIX/shell/sh.c", "source_location": "L111", "receiver": null}, {"caller_nid": "users_vihaannathan_documents_pureunix_shell_sh_shell_execute_line", "callee": "shell_parse", "is_member_call": false, "source_file": "/Users/vihaannathan/Documents/PureUNIX/shell/sh.c", "source_location": "L120", "receiver": null}, {"caller_nid": "users_vihaannathan_documents_pureunix_shell_sh_shell_execute_line", "callee": "memset", "is_member_call": false, "source_file": "/Users/vihaannathan/Documents/PureUNIX/shell/sh.c", "source_location": "L135", "receiver": null}, {"caller_nid": "users_vihaannathan_documents_pureunix_shell_sh_shell_execute_line", "callee": "kfree", "is_member_call": false, "source_file": "/Users/vihaannathan/Documents/PureUNIX/shell/sh.c", "source_location": "L145", "receiver": null}, {"caller_nid": "users_vihaannathan_documents_pureunix_shell_sh_shell_execute_line", "callee": "printf", "is_member_call": false, "source_file": "/Users/vihaannathan/Documents/PureUNIX/shell/sh.c", "source_location": "L149", "receiver": null}, {"caller_nid": "users_vihaannathan_documents_pureunix_shell_sh_shell_execute_line", "callee": "vfs_normalize", "is_member_call": false, "source_file": "/Users/vihaannathan/Documents/PureUNIX/shell/sh.c", "source_location": "L161", "receiver": null}, {"caller_nid": "users_vihaannathan_documents_pureunix_shell_sh_shell_execute_line", "callee": "vfs_write_file", "is_member_call": false, "source_file": "/Users/vihaannathan/Documents/PureUNIX/shell/sh.c", "source_location": "L162", "receiver": null}, {"caller_nid": "users_vihaannathan_documents_pureunix_shell_sh_shell_execute_line", "callee": "printf", "is_member_call": false, "source_file": "/Users/vihaannathan/Documents/PureUNIX/shell/sh.c", "source_location": "L164", "receiver": null}, {"caller_nid": "users_vihaannathan_documents_pureunix_shell_sh_shell_execute_line", "callee": "vga_write_len", "is_member_call": false, "source_file": "/Users/vihaannathan/Documents/PureUNIX/shell/sh.c", "source_location": "L168", "receiver": null}, {"caller_nid": "users_vihaannathan_documents_pureunix_shell_sh_shell_execute_line", "callee": "kfree", "is_member_call": false, "source_file": "/Users/vihaannathan/Documents/PureUNIX/shell/sh.c", "source_location": "L174", "receiver": null}, {"caller_nid": "users_vihaannathan_documents_pureunix_shell_sh_shell_run", "callee": "printf", "is_member_call": false, "source_file": "/Users/vihaannathan/Documents/PureUNIX/shell/sh.c", "source_location": "L182", "receiver": null}, {"caller_nid": "users_vihaannathan_documents_pureunix_shell_sh_shell_run", "callee": "snprintf", "is_member_call": false, "source_file": "/Users/vihaannathan/Documents/PureUNIX/shell/sh.c", "source_location": "L185", "receiver": null}, {"caller_nid": "users_vihaannathan_documents_pureunix_shell_sh_shell_run", "callee": "shell_readline", "is_member_call": false, "source_file": "/Users/vihaannathan/Documents/PureUNIX/shell/sh.c", "source_location": "L186", "receiver": null}]}